{
    "/api/v1/business": {
        "id": 1,
        "businessName": "Bajrang Coal Depot",
        "businessAddress": "Plot No. 3, Street, City, PIN: XXX XXX",
        "businessEmail": "bcd@bcd.com",
        "businessNos": "022 1234 5698",
        "businessLogo": "https://i1.wp.com/realestatebossmamas.com/wp-content/uploads/2018/02/logo-placeholder-1.png?w=200",
        "businessGSTIN": "456789123" 
    },
    "/api/v1/user": {
        "userName": "Yogesh Upadhyay",
        "email": "yogeshh2021@gmail.com",
        "avatar": "https://cdn.icon-icons.com/icons2/1736/PNG/512/4043260-avatar-male-man-portrait_113269.png"
    },
    "/api/v1/businesses" : [
        {
            "id": "1",
            "businessName":"Bajrang Coal Depot"
        },
        {
            "id": 2,
            "businessName": "Bajrang Traders"
        }
    ],
    "/api/v1/parties": [
        {
            "id": "611bdecdfce5836d7b8742fb",
            "name": "string",
            "business": {
                "id": "611bdbc9758caf4c9f489f3d",
                "name": "DEV.il",
                "address": "Somewhere far away",
                "contact_no": "9920064375",
                "creator": {
                "id": "611bdabc758caf4c9f489f3c",
                "name": "Yogesh Upadhyay",
                "email": "user@example.com"
                },
                "employess": []
            },
            "address": "string",
            "contactNo": "string",
            "email": "user@example.com",
            "account": {
                "ifsc": "string",
                "ac_no": "string"
            },
            "type": "string"
        },
        {
            "id": "611bded7fce5836d7b8742fc",
            "name": "string",
            "business": {
                "id": "611bdbc9758caf4c9f489f3d",
                "name": "DEV.il",
                "address": "Somewhere far away",
                "contact_no": "9920064375",
                "creator": {
                "id": "611bdabc758caf4c9f489f3c",
                "name": "Yogesh Upadhyay",
                "email": "user@example.com"
                },
                "employess": []
            },
            "address": "string",
            "contactNo": "string",
            "email": "user@example.com",
            "account": {
                "ifsc": "string",
                "ac_no": "string"
            },
            "type": "string"
        }
    ],
    "/api/v1/stats": {
        "orders": {
            "total": 10,
            "completed": 8
        },
        "collectables": 150000,
        "outstanding": 456200
    }
  }